{
  "Results": {
    "series": [
      {
        "seriesID": "CUUR0000SERE",
        "data": [
          {
            "year": "2003",
            "period": "M13",
            "periodName": "Annual",
            "value": "76.1",
            "aspects": [],
            "footnotes": [
              {}
            ]
          },
          {
            "year": "2003",
            "period": "M12",
            "periodName": "December",
            "value": "74.5",
            "aspects": [],
            "footnotes": [
              {}
            ]
          },
          {
            "year": "2003",
            "period": "M11",
            "periodName": "November",
            "value": "75.1",
            "aspects": [],
            "footnotes": [
              {}
            ]
          },
          {
            "year": "2003",
            "period": "M10",
            "periodName": "October",
            "value": "75.0",
            "aspects": [],
            "footnotes": [
              {}
            ]
          },
          {
            "year": "2003",
            "period": "M09",
            "periodName": "September",
            "value": "75.6",
            "aspects": [],
            "footnotes": [
              {}
            ]
          },
          {
            "year": "2003",
            "period": "M08",
            "periodName": "August",
            "value": "76.0",
            "aspects": [],
            "footnotes": [
              {}
            ]
          },
          {
            "year": "2003",
            "period": "M07",
            "periodName": "July",
            "value": "76.2",
            "aspects": [],
            "footnotes": [
              {}
            ]
          },
          {
            "year": "2003",
            "period": "M06",
            "periodName": "June",
            "value": "76.6",
            "aspects": [],
            "footnotes": [
              {}
            ]
          },
          {
            "year": "2003",
            "period": "M05",
            "periodName": "May",
            "value": "76.6",
            "aspects": [],
            "footnotes": [
              {}
            ]
          },
          {
            "year": "2003",
            "period": "M04",
            "periodName": "April",
            "value": "76.7",
            "aspects": [],
            "footnotes": [
              {}
            ]
          },
          {
            "year": "2003",
            "period": "M03",
            "periodName": "March",
            "value": "77.0",
            "aspects": [],
            "footnotes": [
              {}
            ]
          },
          {
            "year": "2003",
            "period": "M02",
            "periodName": "February",
            "value": "76.6",
            "aspects": [],
            "footnotes": [
              {}
            ]
          },
          {
            "year": "2003",
            "period": "M01",
            "periodName": "January",
            "value": "76.7",
            "aspects": [],
            "footnotes": [
              {}
            ]
          },
          {
            "year": "2002",
            "period": "M13",
            "periodName": "Annual",
            "value": "80.5",
            "aspects": [],
            "footnotes": [
              {}
            ]
          },
          {
            "year": "2002",
            "period": "M12",
            "periodName": "December",
            "value": "77.0",
            "aspects": [],
            "footnotes": [
              {}
            ]
          },
          {
            "year": "2002",
            "period": "M11",
            "periodName": "November",
            "value": "77.1",
            "aspects": [],
            "footnotes": [
              {}
            ]
          },
          {
            "year": "2002",
            "period": "M10",
            "periodName": "October",
            "value": "77.9",
            "aspects": [],
            "footnotes": [
              {}
            ]
          },
          {
            "year": "2002",
            "period": "M09",
            "periodName": "September",
            "value": "78.5",
            "aspects": [],
            "footnotes": [
              {}
            ]
          },
          {
            "year": "2002",
            "period": "M08",
            "periodName": "August",
            "value": "79.1",
            "aspects": [],
            "footnotes": [
              {}
            ]
          },
          {
            "year": "2002",
            "period": "M07",
            "periodName": "July",
            "value": "79.8",
            "aspects": [],
            "footnotes": [
              {}
            ]
          },
          {
            "year": "2002",
            "period": "M06",
            "periodName": "June",
            "value": "80.9",
            "aspects": [],
            "footnotes": [
              {}
            ]
          },
          {
            "year": "2002",
            "period": "M05",
            "periodName": "May",
            "value": "81.7",
            "aspects": [],
            "footnotes": [
              {}
            ]
          },
          {
            "year": "2002",
            "period": "M04",
            "periodName": "April",
            "value": "83.2",
            "aspects": [],
            "footnotes": [
              {}
            ]
          },
          {
            "year": "2002",
            "period": "M03",
            "periodName": "March",
            "value": "83.5",
            "aspects": [],
            "footnotes": [
              {}
            ]
          },
          {
            "year": "2002",
            "period": "M02",
            "periodName": "February",
            "value": "83.7",
            "aspects": [],
            "footnotes": [
              {}
            ]
          },
          {
            "year": "2002",
            "period": "M01",
            "periodName": "January",
            "value": "83.8",
            "aspects": [],
            "footnotes": [
              {}
            ]
          },
          {
            "year": "2001",
            "period": "M13",
            "periodName": "Annual",
            "value": "84.6",
            "aspects": [],
            "footnotes": [
              {}
            ]
          },
          {
            "year": "2001",
            "period": "M12",
            "periodName": "December",
            "value": "83.1",
            "aspects": [],
            "footnotes": [
              {}
            ]
          },
          {
            "year": "2001",
            "period": "M11",
            "periodName": "November",
            "value": "84.1",
            "aspects": [],
            "footnotes": [
              {}
            ]
          },
          {
            "year": "2001",
            "period": "M10",
            "periodName": "October",
            "value": "84.7",
            "aspects": [],
            "footnotes": [
              {}
            ]
          },
          {
            "year": "2001",
            "period": "M09",
            "periodName": "September",
            "value": "84.6",
            "aspects": [],
            "footnotes": [
              {}
            ]
          },
          {
            "year": "2001",
            "period": "M08",
            "periodName": "August",
            "value": "84.3",
            "aspects": [],
            "footnotes": [
              {}
            ]
          },
          {
            "year": "2001",
            "period": "M07",
            "periodName": "July",
            "value": "84.6",
            "aspects": [],
            "footnotes": [
              {}
            ]
          },
          {
            "year": "2001",
            "period": "M06",
            "periodName": "June",
            "value": "84.7",
            "aspects": [],
            "footnotes": [
              {}
            ]
          },
          {
            "year": "2001",
            "period": "M05",
            "periodName": "May",
            "value": "85.0",
            "aspects": [],
            "footnotes": [
              {}
            ]
          },
          {
            "year": "2001",
            "period": "M04",
            "periodName": "April",
            "value": "84.9",
            "aspects": [],
            "footnotes": [
              {}
            ]
          },
          {
            "year": "2001",
            "period": "M03",
            "periodName": "March",
            "value": "84.1",
            "aspects": [],
            "footnotes": [
              {}
            ]
          },
          {
            "year": "2001",
            "period": "M02",
            "periodName": "February",
            "value": "85.2",
            "aspects": [],
            "footnotes": [
              {}
            ]
          },
          {
            "year": "2001",
            "period": "M01",
            "periodName": "January",
            "value": "85.8",
            "aspects": [],
            "footnotes": [
              {}
            ]
          },
          {
            "year": "2000",
            "period": "M13",
            "periodName": "Annual",
            "value": "87.8",
            "aspects": [],
            "footnotes": [
              {}
            ]
          },
          {
            "year": "2000",
            "period": "M12",
            "periodName": "December",
            "value": "86.4",
            "aspects": [],
            "footnotes": [
              {}
            ]
          },
          {
            "year": "2000",
            "period": "M11",
            "periodName": "November",
            "value": "86.6",
            "aspects": [],
            "footnotes": [
              {}
            ]
          },
          {
            "year": "2000",
            "period": "M10",
            "periodName": "October",
            "value": "87.2",
            "aspects": [],
            "footnotes": [
              {}
            ]
          },
          {
            "year": "2000",
            "period": "M09",
            "periodName": "September",
            "value": "87.0",
            "aspects": [],
            "footnotes": [
              {}
            ]
          },
          {
            "year": "2000",
            "period": "M08",
            "periodName": "August",
            "value": "87.6",
            "aspects": [],
            "footnotes": [
              {}
            ]
          },
          {
            "year": "2000",
            "period": "M07",
            "periodName": "July",
            "value": "87.8",
            "aspects": [],
            "footnotes": [
              {}
            ]
          },
          {
            "year": "2000",
            "period": "M06",
            "periodName": "June",
            "value": "87.8",
            "aspects": [],
            "footnotes": [
              {}
            ]
          },
          {
            "year": "2000",
            "period": "M05",
            "periodName": "May",
            "value": "88.3",
            "aspects": [],
            "footnotes": [
              {}
            ]
          },
          {
            "year": "2000",
            "period": "M04",
            "periodName": "April",
            "value": "88.4",
            "aspects": [],
            "footnotes": [
              {}
            ]
          },
          {
            "year": "2000",
            "period": "M03",
            "periodName": "March",
            "value": "88.7",
            "aspects": [],
            "footnotes": [
              {}
            ]
          },
          {
            "year": "2000",
            "period": "M02",
            "periodName": "February",
            "value": "88.7",
            "aspects": [],
            "footnotes": [
              {}
            ]
          },
          {
            "year": "2000",
            "period": "M01",
            "periodName": "January",
            "value": "88.6",
            "aspects": [],
            "footnotes": [
              {}
            ]
          },
          {
            "year": "1999",
            "period": "M13",
            "periodName": "Annual",
            "value": "92.3",
            "aspects": [],
            "footnotes": [
              {}
            ]
          },
          {
            "year": "1999",
            "period": "M12",
            "periodName": "December",
            "value": "88.7",
            "aspects": [],
            "footnotes": [
              {}
            ]
          },
          {
            "year": "1999",
            "period": "M11",
            "periodName": "November",
            "value": "89.1",
            "aspects": [],
            "footnotes": [
              {}
            ]
          },
          {
            "year": "1999",
            "period": "M10",
            "periodName": "October",
            "value": "90.3",
            "aspects": [],
            "footnotes": [
              {}
            ]
          },
          {
            "year": "1999",
            "period": "M09",
            "periodName": "September",
            "value": "90.5",
            "aspects": [],
            "footnotes": [
              {}
            ]
          },
          {
            "year": "1999",
            "period": "M08",
            "periodName": "August",
            "value": "92.2",
            "aspects": [],
            "footnotes": [
              {}
            ]
          },
          {
            "year": "1999",
            "period": "M07",
            "periodName": "July",
            "value": "93.0",
            "aspects": [],
            "footnotes": [
              {}
            ]
          },
          {
            "year": "1999",
            "period": "M06",
            "periodName": "June",
            "value": "93.5",
            "aspects": [],
            "footnotes": [
              {}
            ]
          },
          {
            "year": "1999",
            "period": "M05",
            "periodName": "May",
            "value": "93.2",
            "aspects": [],
            "footnotes": [
              {}
            ]
          },
          {
            "year": "1999",
            "period": "M04",
            "periodName": "April",
            "value": "93.8",
            "aspects": [],
            "footnotes": [
              {}
            ]
          },
          {
            "year": "1999",
            "period": "M03",
            "periodName": "March",
            "value": "94.1",
            "aspects": [],
            "footnotes": [
              {}
            ]
          },
          {
            "year": "1999",
            "period": "M02",
            "periodName": "February",
            "value": "94.3",
            "aspects": [],
            "footnotes": [
              {}
            ]
          },
          {
            "year": "1999",
            "period": "M01",
            "periodName": "January",
            "value": "94.8",
            "aspects": [],
            "footnotes": [
              {}
            ]
          },
          {
            "year": "1998",
            "period": "M13",
            "periodName": "Annual",
            "value": "97.1",
            "aspects": [],
            "footnotes": [
              {}
            ]
          },
          {
            "year": "1998",
            "period": "M12",
            "periodName": "December",
            "value": "95.0",
            "aspects": [],
            "footnotes": [
              {}
            ]
          },
          {
            "year": "1998",
            "period": "M11",
            "periodName": "November",
            "value": "95.2",
            "aspects": [],
            "footnotes": [
              {}
            ]
          },
          {
            "year": "1998",
            "period": "M10",
            "periodName": "October",
            "value": "95.8",
            "aspects": [],
            "footnotes": [
              {}
            ]
          },
          {
            "year": "1998",
            "period": "M09",
            "periodName": "September",
            "value": "96.2",
            "aspects": [],
            "footnotes": [
              {}
            ]
          },
          {
            "year": "1998",
            "period": "M08",
            "periodName": "August",
            "value": "96.6",
            "aspects": [],
            "footnotes": [
              {}
            ]
          },
          {
            "year": "1998",
            "period": "M07",
            "periodName": "July",
            "value": "97.0",
            "aspects": [],
            "footnotes": [
              {}
            ]
          },
          {
            "year": "1998",
            "period": "M06",
            "periodName": "June",
            "value": "97.3",
            "aspects": [],
            "footnotes": [
              {}
            ]
          },
          {
            "year": "1998",
            "period": "M05",
            "periodName": "May",
            "value": "97.5",
            "aspects": [],
            "footnotes": [
              {}
            ]
          },
          {
            "year": "1998",
            "period": "M04",
            "periodName": "April",
            "value": "98.3",
            "aspects": [],
            "footnotes": [
              {}
            ]
          },
          {
            "year": "1998",
            "period": "M03",
            "periodName": "March",
            "value": "98.7",
            "aspects": [],
            "footnotes": [
              {}
            ]
          },
          {
            "year": "1998",
            "period": "M02",
            "periodName": "February",
            "value": "98.8",
            "aspects": [],
            "footnotes": [
              {}
            ]
          },
          {
            "year": "1998",
            "period": "M01",
            "periodName": "January",
            "value": "99.1",
            "aspects": [],
            "footnotes": [
              {}
            ]
          },
          {
            "year": "1997",
            "period": "M12",
            "periodName": "December",
            "value": "100.0",
            "aspects": [],
            "footnotes": [
              {}
            ]
          }
        ]
      }
    ]
  }
}