{
  "Results": {
    "series": [
      {
        "seriesID": "CUUR0000SS14011",
        "data": [
          {
            "year": "2025",
            "period": "M06",
            "periodName": "June",
            "latest": "true",
            "value": "258.583",
            "aspects": [
              {
                "name": "Historical reference to 12 month % change",
                "value": "L-Mar. 2025",
                "footnotes": [
                  {}
                ]
              },
              {
                "name": "Median Standard Error 12 Month Change",
                "value": "1.67",
                "footnotes": [
                  {}
                ]
              },
              {
                "name": "12 month % change prior to the current month",
                "value": "-0.2",
                "footnotes": [
                  {}
                ]
              }
            ],
            "footnotes": [
              {}
            ]
          },
          {
            "year": "2025",
            "period": "M05",
            "periodName": "May",
            "value": "255.912",
            "aspects": [
              {
                "name": "Historical reference to 12 month % change",
                "value": "S-EVER",
                "footnotes": [
                  {}
                ]
              },
              {
                "name": "Median Standard Error 12 Month Change",
                "value": "1.67",
                "footnotes": [
                  {}
                ]
              },
              {
                "name": "12 month % change prior to the current month",
                "value": "-",
                "footnotes": [
                  {}
                ]
              }
            ],
            "footnotes": [
              {}
            ]
          },
          {
            "year": "2025",
            "period": "M04",
            "periodName": "April",
            "value": "257.355",
            "aspects": [
              {
                "name": "Historical reference to 12 month % change",
                "value": "S-Jun. 2018",
                "footnotes": [
                  {}
                ]
              },
              {
                "name": "Median Standard Error 12 Month Change",
                "value": "1.67",
                "footnotes": [
                  {}
                ]
              },
              {
                "name": "12 month % change prior to the current month",
                "value": "-4.5",
                "footnotes": [
                  {}
                ]
              }
            ],
            "footnotes": [
              {}
            ]
          },
          {
            "year": "2025",
            "period": "M03",
            "periodName": "March",
            "value": "264.051",
            "aspects": [
              {
                "name": "Historical reference to 12 month % change",
                "value": "L-May 2024",
                "footnotes": [
                  {}
                ]
              },
              {
                "name": "Median Standard Error 12 Month Change",
                "value": "1.67",
                "footnotes": [
                  {}
                ]
              },
              {
                "name": "12 month % change prior to the current month",
                "value": "0.2",
                "footnotes": [
                  {}
                ]
              }
            ],
            "footnotes": [
              {}
            ]
          },
          {
            "year": "2025",
            "period": "M02",
            "periodName": "February",
            "value": "262.279",
            "aspects": [
              {
                "name": "Historical reference to 12 month % change",
                "value": "L-May 2024",
                "footnotes": [
                  {}
                ]
              },
              {
                "name": "Median Standard Error 12 Month Change",
                "value": "1.67",
                "footnotes": [
                  {}
                ]
              },
              {
                "name": "12 month % change prior to the current month",
                "value": "0.2",
                "footnotes": [
                  {}
                ]
              }
            ],
            "footnotes": [
              {}
            ]
          },
          {
            "year": "2025",
            "period": "M01",
            "periodName": "January",
            "value": "255.631",
            "aspects": [
              {
                "name": "Historical reference to 12 month % change",
                "value": "S-Oct. 2018",
                "footnotes": [
                  {}
                ]
              },
              {
                "name": "Median Standard Error 12 Month Change",
                "value": "1.67",
                "footnotes": [
                  {}
                ]
              },
              {
                "name": "12 month % change prior to the current month",
                "value": "-3.5",
                "footnotes": [
                  {}
                ]
              }
            ],
            "footnotes": [
              {}
            ]
          },
          {
            "year": "2024",
            "period": "M13",
            "periodName": "Annual",
            "value": "264.022",
            "aspects": [],
            "footnotes": [
              {}
            ]
          },
          {
            "year": "2024",
            "period": "M12",
            "periodName": "December",
            "value": "255.914",
            "aspects": [
              {
                "name": "Historical reference to 12 month % change",
                "value": "S-Sep. 2024",
                "footnotes": [
                  {}
                ]
              },
              {
                "name": "Median Standard Error 12 Month Change",
                "value": "2.53",
                "footnotes": [
                  {}
                ]
              },
              {
                "name": "12 month % change prior to the current month",
                "value": "-2.2",
                "footnotes": [
                  {}
                ]
              }
            ],
            "footnotes": [
              {}
            ]
          },
          {
            "year": "2024",
            "period": "M11",
            "periodName": "November",
            "value": "255.931",
            "aspects": [
              {
                "name": "Historical reference to 12 month % change",
                "value": "S-Sep. 2024",
                "footnotes": [
                  {}
                ]
              },
              {
                "name": "Median Standard Error 12 Month Change",
                "value": "2.53",
                "footnotes": [
                  {}
                ]
              },
              {
                "name": "12 month % change prior to the current month",
                "value": "-2.2",
                "footnotes": [
                  {}
                ]
              }
            ],
            "footnotes": [
              {}
            ]
          },
          {
            "year": "2024",
            "period": "M10",
            "periodName": "October",
            "value": "265.636",
            "aspects": [
              {
                "name": "Historical reference to 12 month % change",
                "value": "L-Aug. 2024",
                "footnotes": [
                  {}
                ]
              },
              {
                "name": "Median Standard Error 12 Month Change",
                "value": "2.53",
                "footnotes": [
                  {}
                ]
              },
              {
                "name": "12 month % change prior to the current month",
                "value": "-1.2",
                "footnotes": [
                  {}
                ]
              }
            ],
            "footnotes": [
              {}
            ]
          },
          {
            "year": "2024",
            "period": "M09",
            "periodName": "September",
            "value": "262.199",
            "aspects": [
              {
                "name": "Historical reference to 12 month % change",
                "value": "S-Jan. 2019",
                "footnotes": [
                  {}
                ]
              },
              {
                "name": "Median Standard Error 12 Month Change",
                "value": "2.53",
                "footnotes": [
                  {}
                ]
              },
              {
                "name": "12 month % change prior to the current month",
                "value": "-3.1",
                "footnotes": [
                  {}
                ]
              }
            ],
            "footnotes": [
              {}
            ]
          },
          {
            "year": "2024",
            "period": "M08",
            "periodName": "August",
            "value": "265.562",
            "aspects": [
              {
                "name": "Historical reference to 12 month % change",
                "value": "-",
                "footnotes": [
                  {}
                ]
              },
              {
                "name": "Median Standard Error 12 Month Change",
                "value": "2.53",
                "footnotes": [
                  {}
                ]
              },
              {
                "name": "12 month % change prior to the current month",
                "value": "-",
                "footnotes": [
                  {}
                ]
              }
            ],
            "footnotes": [
              {}
            ]
          },
          {
            "year": "2024",
            "period": "M07",
            "periodName": "July",
            "value": "267.184",
            "aspects": [
              {
                "name": "Historical reference to 12 month % change",
                "value": "L-May 2024",
                "footnotes": [
                  {}
                ]
              },
              {
                "name": "Median Standard Error 12 Month Change",
                "value": "2.53",
                "footnotes": [
                  {}
                ]
              },
              {
                "name": "12 month % change prior to the current month",
                "value": "0.2",
                "footnotes": [
                  {}
                ]
              }
            ],
            "footnotes": [
              {}
            ]
          },
          {
            "year": "2024",
            "period": "M06",
            "periodName": "June",
            "value": "266.265",
            "aspects": [
              {
                "name": "Historical reference to 12 month % change",
                "value": "S-Jan. 2019",
                "footnotes": [
                  {}
                ]
              },
              {
                "name": "Median Standard Error 12 Month Change",
                "value": "2.53",
                "footnotes": [
                  {}
                ]
              },
              {
                "name": "12 month % change prior to the current month",
                "value": "-3.1",
                "footnotes": [
                  {}
                ]
              }
            ],
            "footnotes": [
              {}
            ]
          },
          {
            "year": "2024",
            "period": "M05",
            "periodName": "May",
            "value": "269.256",
            "aspects": [
              {
                "name": "Historical reference to 12 month % change",
                "value": "S-Oct. 2021",
                "footnotes": [
                  {}
                ]
              },
              {
                "name": "Median Standard Error 12 Month Change",
                "value": "2.53",
                "footnotes": [
                  {}
                ]
              },
              {
                "name": "12 month % change prior to the current month",
                "value": "-0.3",
                "footnotes": [
                  {}
                ]
              }
            ],
            "footnotes": [
              {}
            ]
          },
          {
            "year": "2024",
            "period": "M04",
            "periodName": "April",
            "value": "267.145",
            "aspects": [
              {
                "name": "Historical reference to 12 month % change",
                "value": "L-Jan. 2024",
                "footnotes": [
                  {}
                ]
              },
              {
                "name": "Median Standard Error 12 Month Change",
                "value": "2.53",
                "footnotes": [
                  {}
                ]
              },
              {
                "name": "12 month % change prior to the current month",
                "value": "5.0",
                "footnotes": [
                  {}
                ]
              }
            ],
            "footnotes": [
              {}
            ]
          },
          {
            "year": "2024",
            "period": "M03",
            "periodName": "March",
            "value": "264.553",
            "aspects": [
              {
                "name": "Historical reference to 12 month % change",
                "value": "L-Jan. 2024",
                "footnotes": [
                  {}
                ]
              },
              {
                "name": "Median Standard Error 12 Month Change",
                "value": "2.53",
                "footnotes": [
                  {}
                ]
              },
              {
                "name": "12 month % change prior to the current month",
                "value": "5.0",
                "footnotes": [
                  {}
                ]
              }
            ],
            "footnotes": [
              {}
            ]
          },
          {
            "year": "2024",
            "period": "M02",
            "periodName": "February",
            "value": "264.659",
            "aspects": [
              {
                "name": "Historical reference to 12 month % change",
                "value": "S-Nov. 2021",
                "footnotes": [
                  {}
                ]
              },
              {
                "name": "Median Standard Error 12 Month Change",
                "value": "2.53",
                "footnotes": [
                  {}
                ]
              },
              {
                "name": "12 month % change prior to the current month",
                "value": "0.5",
                "footnotes": [
                  {}
                ]
              }
            ],
            "footnotes": [
              {}
            ]
          },
          {
            "year": "2024",
            "period": "M01",
            "periodName": "January",
            "value": "263.955",
            "aspects": [
              {
                "name": "Historical reference to 12 month % change",
                "value": "S-Jan. 2022",
                "footnotes": [
                  {}
                ]
              },
              {
                "name": "Median Standard Error 12 Month Change",
                "value": "2.53",
                "footnotes": [
                  {}
                ]
              },
              {
                "name": "12 month % change prior to the current month",
                "value": "2.7",
                "footnotes": [
                  {}
                ]
              }
            ],
            "footnotes": [
              {}
            ]
          }
        ]
      }
    ]
  }
}