{
  "Results": {
    "series": [
      {
        "seriesID": "CUUS0000SEFP02",
        "data": [
          {
            "year": "2023",
            "period": "S03",
            "periodName": "Annual",
            "value": "155.538",
            "aspects": [],
            "footnotes": [
              {}
            ]
          },
          {
            "year": "2023",
            "period": "S02",
            "periodName": "2nd Half",
            "value": "156.447",
            "aspects": [],
            "footnotes": [
              {}
            ]
          },
          {
            "year": "2023",
            "period": "S01",
            "periodName": "1st Half",
            "value": "154.628",
            "aspects": [],
            "footnotes": [
              {}
            ]
          },
          {
            "year": "2022",
            "period": "S03",
            "periodName": "Annual",
            "value": "145.027",
            "aspects": [],
            "footnotes": [
              {}
            ]
          },
          {
            "year": "2022",
            "period": "S02",
            "periodName": "2nd Half",
            "value": "149.273",
            "aspects": [],
            "footnotes": [
              {}
            ]
          },
          {
            "year": "2022",
            "period": "S01",
            "periodName": "1st Half",
            "value": "140.782",
            "aspects": [],
            "footnotes": [
              {}
            ]
          },
          {
            "year": "2021",
            "period": "S03",
            "periodName": "Annual",
            "value": "134.985",
            "aspects": [],
            "footnotes": [
              {}
            ]
          },
          {
            "year": "2021",
            "period": "S02",
            "periodName": "2nd Half",
            "value": "135.833",
            "aspects": [],
            "footnotes": [
              {}
            ]
          },
          {
            "year": "2021",
            "period": "S01",
            "periodName": "1st Half",
            "value": "134.136",
            "aspects": [],
            "footnotes": [
              {}
            ]
          },
          {
            "year": "2020",
            "period": "S03",
            "periodName": "Annual",
            "value": "132.622",
            "aspects": [],
            "footnotes": [
              {}
            ]
          },
          {
            "year": "2020",
            "period": "S02",
            "periodName": "2nd Half",
            "value": "132.823",
            "aspects": [],
            "footnotes": [
              {}
            ]
          },
          {
            "year": "2020",
            "period": "S01",
            "periodName": "1st Half",
            "value": "132.421",
            "aspects": [],
            "footnotes": [
              {}
            ]
          },
          {
            "year": "2019",
            "period": "S03",
            "periodName": "Annual",
            "value": "130.118",
            "aspects": [],
            "footnotes": [
              {}
            ]
          },
          {
            "year": "2019",
            "period": "S02",
            "periodName": "2nd Half",
            "value": "130.534",
            "aspects": [],
            "footnotes": [
              {}
            ]
          },
          {
            "year": "2019",
            "period": "S01",
            "periodName": "1st Half",
            "value": "129.702",
            "aspects": [],
            "footnotes": [
              {}
            ]
          },
          {
            "year": "2018",
            "period": "S03",
            "periodName": "Annual",
            "value": "128.619",
            "aspects": [],
            "footnotes": [
              {}
            ]
          },
          {
            "year": "2018",
            "period": "S02",
            "periodName": "2nd Half",
            "value": "128.842",
            "aspects": [],
            "footnotes": [
              {}
            ]
          },
          {
            "year": "2018",
            "period": "S01",
            "periodName": "1st Half",
            "value": "128.397",
            "aspects": [],
            "footnotes": [
              {}
            ]
          }
        ]
      }
    ]
  }
}